jacket_cli/__init__.py
jacket_cli/__main__.py
jacket_cli/utils.py
model_jacket-0.2.0.dist-info/METADATA
model_jacket-0.2.0.dist-info/WHEEL
model_jacket-0.2.0.dist-info/entry_points.txt
model_jacket-0.2.0.dist-info/top_level.txt
model_jacket-0.2.0.dist-info/RECORD
