Metadata-Version: 2.1
Name: model-jacket
Version: 0.2.0
Summary: Package any ML model into a scalable, observable FastAPI service
Home-page: https://github.com/shahwarcodes/model-jacket
Author: Shahwar Saleem
Author-email: saleemshahwar@email.com
Classifier: Programming Language :: Python :: 3
Classifier: License :: OSI Approved :: MIT License
Classifier: Operating System :: OS Independent
Requires-Python: >=3.8
Requires-Dist: fastapi
Requires-Dist: uvicorn[standard]
Requires-Dist: pydantic
Requires-Dist: prometheus-client
Requires-Dist: torch
Requires-Dist: onnxruntime
Requires-Dist: scikit-learn
Requires-Dist: joblib
